saeli/__init__.py
saeli/saeli_module.py
saeligram-0.0.31.dist-info/METADATA
saeligram-0.0.31.dist-info/WHEEL
saeligram-0.0.31.dist-info/top_level.txt
saeligram-0.0.31.dist-info/RECORD
